pyChp/__init__.py
pychp-0.0.1a1.dist-info/METADATA
pychp-0.0.1a1.dist-info/WHEEL
pychp-0.0.1a1.dist-info/top_level.txt
pychp-0.0.1a1.dist-info/RECORD
