Metadata-Version: 2.4
Name: pyChp
Version: 0.0.1a1
Summary: A Python Toolkit for the Chinese Pharmacopoeia
Home-page: https://github.com/yourusername/pyChp
Author: pyChp Team
Author-email: pyChp Team <team@pychp.org>
License: MIT
Project-URL: Homepage, https://github.com/yourusername/pyChp
Project-URL: Repository, https://github.com/yourusername/pyChp
Project-URL: Bug Reports, https://github.com/yourusername/pyChp/issues
Classifier: Development Status :: 3 - Alpha
Classifier: Intended Audience :: Healthcare Industry
Classifier: Intended Audience :: Science/Research
Classifier: License :: OSI Approved :: MIT License
Classifier: Operating System :: OS Independent
Classifier: Programming Language :: Python :: 3
Classifier: Programming Language :: Python :: 3.8
Classifier: Programming Language :: Python :: 3.9
Classifier: Programming Language :: Python :: 3.10
Classifier: Programming Language :: Python :: 3.11
Classifier: Topic :: Scientific/Engineering
Classifier: Topic :: Scientific/Engineering :: Medical Science Apps.
Requires-Python: >=3.8
Provides-Extra: dev
Requires-Dist: pytest>=6.0; extra == "dev"
Requires-Dist: black; extra == "dev"
Requires-Dist: flake8; extra == "dev"
Dynamic: author
Dynamic: home-page
Dynamic: requires-python
